hello_world/__init__.py
hello_world/hello.py
massie123-0.0.1.dist-info/METADATA
massie123-0.0.1.dist-info/WHEEL
massie123-0.0.1.dist-info/top_level.txt
massie123-0.0.1.dist-info/RECORD
